README.rst
setup.cfg
setup.py
steelconnection/__init__.py
steelconnection/__main__.py
steelconnection/about.py
steelconnection/api.py
steelconnection/exceptions.py
steelconnection/image_download.py
steelconnection/input_tools.py
steelconnection/lookup.py
steelconnection.egg-info/PKG-INFO
steelconnection.egg-info/SOURCES.txt
steelconnection.egg-info/dependency_links.txt
steelconnection.egg-info/requires.txt
steelconnection.egg-info/top_level.txt