Metadata-Version: 2.1
Name: steelconnection
Version: 1.1.7
Summary: Simplify access to the Riverbed SteelConnect REST API.
Home-page: https://github.com/grelleum/SteelConnection
Author: Greg Mueller
Author-email: steelconnection@grelleum.com
License: MIT
Keywords: SteelConnect,REST,API,Riverbed,Grelleum
Platform: UNKNOWN
Classifier: Programming Language :: Python :: 2
Classifier: Programming Language :: Python :: 2.7
Classifier: Programming Language :: Python :: 3
Classifier: Programming Language :: Python :: 3.5
Classifier: Programming Language :: Python :: 3.6
Classifier: Programming Language :: Python :: 3.7
Classifier: Programming Language :: Python :: 3.8
Classifier: License :: OSI Approved :: MIT License
Classifier: Operating System :: OS Independent
